schematools/__init__.py
schematools/apache_arrow.py
schematools/jsonschema/__init__.py
schematools/jsonschema/flatten.py
schematools/jsonschema/parse.py
schematools/jsonschema/types.py
py_schematools-0.0.3.dist-info/METADATA
py_schematools-0.0.3.dist-info/WHEEL
py_schematools-0.0.3.dist-info/RECORD
